{
  "slug": "makhtesh-ramon",
  "title": "מכתש רמון — מדריך ליום שלם",
  "description": "מדריך מקיף ליום שלם במכתש רמון — מסלולי הליכה, נקודות תצפית, בעלי חיים, גיאולוגיה ייחודית וטיפים מעשיים לביקור מושלם",
  "category": "desert",
  "tags": ["מכתש רמון", "מצפה רמון", "טיולים בנגב", "גיאולוגיה", "שמורת טבע", "מדבר", "מסלולי הליכה"],
  "publishDate": "2026-06-01",
  "heroEmoji": "🏜️",
  "content": "<h2>מכתש רמון — תופעה גיאולוגית שקיימת רק בישראל</h2><p>מכתש רמון הוא <strong>המכתש הגדול בעולם</strong> — 40 ק\"מ אורך, 2-10 ק\"מ רוחב, ו-300 מטר עומק. אבל מה שבאמת מיוחד בו הוא שהוא <strong>לא קיים בשום מקום אחר על פני כדור הארץ</strong>. מכתש — בניגוד למכתש פגיעה או קלדרה וולקנית — נוצר מתהליך שחיקה ייחודי שחשף שכבות סלע בנות מאות מיליוני שנים.</p><p>כשאתם עומדים על שפת המכתש ומביטים פנימה, אתם רואים <strong>ספר היסטוריה גיאולוגי פתוח</strong>. שכבות צבעוניות של חול, גיר, דולומיט ובזלת מספרות את סיפור כדור הארץ לאורך 220 מיליון שנה. זה פשוט מרהיב.</p><p>המכתש נמצא ב<a href='/article/midbar-negev'>מדבר הנגב</a>, ליד העיירה מצפה רמון. הוא נגיש, מתוחזק היטב, ומציע חוויות לכל סוגי המטיילים — ממשפחות עם ילדים קטנים ועד מטיילים מנוסים שמחפשים אתגר.</p><h2>תוכנית יום שלם — מהבוקר עד הערב</h2><p>הנה תוכנית אופטימלית ליום במכתש, מהבוקר עד <a href='/article/kokhavim-bamidbar'>צפייה בכוכבים</a> בערב:</p><p><strong>07:00-08:00 — מצפה הגמלים ותצפית הבוקר</strong></p><p>התחילו את היום עם תצפית מנקודת התצפית הראשית של מצפה רמון, ממש על שפת המכתש. באור הבוקר, הצבעים של השכבות הגיאולוגיות בוהקים במיוחד — אדומים, צהובים, חומים ולבנים. צלמו עכשיו, כי באור הצהריים הכל נראה שטוח יותר.</p><p><strong>08:00-09:00 — מרכז המבקרים</strong></p><p>מרכז המבקרים של מכתש רמון מציע <strong>סרט תלת-ממד</strong> על היווצרות המכתש, תצוגות אינטראקטיביות ומודלים גיאולוגיים. מומלץ במיוחד למשפחות ולמי שרוצה להבין מה הוא רואה לפני שיורד למכתש.</p><p><strong>09:00-12:00 — מסלול הליכה בתוך המכתש</strong></p><p>יורדים למכתש דרך מעלה הר ארדון (בכביש או ברגל). בתוך המכתש, כמה אופציות:</p><ul><li><strong>הקרפנטריה</strong> (שעה-שעתיים) — מסלול קצר שמוביל לתצורות עץ מאובן בנות 200 מיליון שנה. עצים שהפכו לסלע, עם טבעות גדילה גלויות. <strong>חובה לראות</strong></li><li><strong>סנפיר הכריש</strong> (שעה) — תצורת סלע שנראית בדיוק כמו סנפיר כריש ענק שבוקע מהאדמה. מושלם לתמונות</li><li><strong>הגבעות הצבעוניות</strong> (שעתיים) — מסלול בין גבעות חול צבעוניות — אדום, צהוב, ירוק, סגול. הצבעים נובעים ממינרלים שונים בסלע. נראה כמו ציור</li><li><strong>מעלה מחמל המלא</strong> (3-4 שעות) — למטיילים מנוסים. עלייה חזרה מתוך המכתש לשפה. מאתגר פיזית אבל התגמול — נוף על כל המכתש — שווה כל טיפת זיעה</li></ul><p><strong>12:00-14:00 — ארוחת צהריים והפסקה</strong></p><p>חזרו למצפה רמון לארוחה. העיירה מציעה כמה מסעדות טובות ובתי קפה. <strong>טיפ:</strong> קנו אוכל לפני היום ואכלו פיקניק בתוך המכתש — חוויה אחרת לגמרי.</p><p><strong>14:00-16:00 — אופניים או ג׳יפים</strong></p><p>אחר הצהריים, אחרי שהרגליים נחו, יש שתי אופציות מצוינות:</p><ul><li><strong>סיור ג׳יפים</strong> — מפעילים מקומיים מציעים סיורים של 2-3 שעות שמגיעים למקומות שלא נגישים ברגל. מומלץ במיוחד למשפחות</li><li><strong>אופני שטח</strong> — המכתש מציע שבילים מסומנים לרכיבה. אפשר לשכור אופניים במצפה רמון. הרכיבה בתוך המכתש עם הנוף הפתוח היא חוויה אדירה</li></ul><p><strong>16:00-17:30 — ביו רמון</strong></p><p>מרכז ביו רמון הוא מקלט לבעלי חיים מדבריים. כאן תפגשו <strong>צבועים, זאבים, שועלים, נשרים ויענים</strong> — חלקם שוקמו ולא יכולים לחזור לטבע. מושלם לילדים, ומרתק גם למבוגרים.</p><p><strong>17:30-19:00 — שקיעה מהשפה</strong></p><p>חזרו לנקודת התצפית לשקיעה. השקיעה במכתש היא <strong>תופעה</strong> — השמש השוקעת צובעת את שכבות הסלע בגוונים של זהב, כתום ואדום עמוק. זה אחד המראות היפים בישראל, בלי ספק.</p><h2>חיות בר שתפגשו</h2><p>מכתש רמון הוא <strong>שמורת טבע פעילה</strong> עם מגוון מפתיע של חיות בר:</p><ul><li><strong>יעלים</strong> — תראו אותם כמעט בוודאות. הם מסתובבים ליד השפה ובתוך המכתש. לא להאכיל!</li><li><strong>צבי מדבר</strong> — יותר ביישנים, אבל בשעות הבוקר המוקדמות יש סיכוי לראות</li><li><strong>נשרים</strong> — נשר מקראי ונשר שחור חוזרים לאזור בזכות תוכניות שימור. מרהיב לראות אותם מרחפים</li><li><strong>שועלים</strong> — שועל צוקים (שועל רופל) ושועל חולות. נראים בעיקר בשקיעה ובלילה</li><li><strong>זאבים</strong> — נדירים לצפייה, אבל קיימים. אם יש לכם מזל ותראו זאב ערבי — זו חוויה בלתי נשכחת</li></ul><h2>טיפים מעשיים לביקור</h2><p>כמה דברים שישדרגו את היום שלכם:</p><p><strong>הגעה</strong> — מצפה רמון נמצאת כשעתיים מבאר שבע וכשלוש שעות מתל אביב. <strong>בדלק מלא</strong> — אין הרבה תחנות דלק בדרך. כביש 40 חוצה את המכתש ומציע תצפיות מהכביש.</p><p><strong>מים</strong> — מינימום 3-4 ליטר לאדם. אין מים בתוך המכתש. <a href='/article/midbar-negev'>כללי המדבר</a> חלים כאן במלואם.</p><p><strong>לינה</strong> — מצפה רמון מציעה כמה אופציות <a href='/article/yamlaila-bamidbar'>לינה</a> — מצימרים מפנקים ועד <strong>גלמפינג על שפת המכתש</strong>. הישארו ללילה כדי לראות את <a href='/article/kokhavim-bamidbar'>הכוכבים</a> — זה שווה כל שקל.</p><p><strong>נעליים</strong> — נעלי הליכה סגורות ויציבות. הקרקע בתוך המכתש סלעית ולא אחידה. סנדלים זה מתכון לפציעה.</p><p>מכתש רמון הוא מקום שצריך לחזור אליו — כל עונה נראית אחרת, כל שעה ביום מציעה אור שונה. אם אתם מתכננים <a href='/article/khavaya-beduit'>חוויה מדברית</a> שלמה, שלבו את המכתש עם <a href='/article/eilat-snorkeling'>יום באילת</a> לטיול שמשלב מדבר וים בחוויה אחת בלתי נשכחת.</p>",
  "relatedSlugs": ["midbar-negev", "kokhavim-bamidbar", "yamlaila-bamidbar", "eilat-madrich", "eilat-snorkeling", "khavaya-beduit"]
}
